alliance_platform/pdf/__init__.py
alliance_platform/pdf/apps.py
alliance_platform/pdf/decorators.py
alliance_platform/pdf/render.py
alliance_platform/pdf/render_process.py
alliance_platform/pdf/request_handlers.py
alliance_platform/pdf/settings.py
alliance_platform/pdf/utils.py
alliance_platform/py.typed
alliance_platform_pdf-0.0.2.dist-info/METADATA
alliance_platform_pdf-0.0.2.dist-info/WHEEL
alliance_platform_pdf-0.0.2.dist-info/entry_points.txt
alliance_platform_pdf-0.0.2.dist-info/RECORD
