Metadata-Version: 2.1
Name: alliance-platform-pdf
Version: 0.0.2
Summary: Alliance Platform PDF
Author-Email: Alliance Software <support@alliancesoftware.com.au>
License: BSD-2-Clause
Requires-Python: >=3.11
Requires-Dist: alliance-platform-core
Requires-Dist: alliance-platform-frontend
Requires-Dist: playwright
Requires-Dist: Django>=4.2.11
Requires-Dist: django-allianceutils>=4.0
